su/__init__.py
su/base.py
su-0.0.8.dist-info/licenses/LICENSE
su-0.0.8.dist-info/METADATA
su-0.0.8.dist-info/WHEEL
su-0.0.8.dist-info/top_level.txt
su-0.0.8.dist-info/RECORD
