Metadata-Version: 2.4
Name: su
Version: 0.0.8
Summary: Speech Utils
Home-page: https://github.com/thorwhalen/su
Author: Thor Whalen
License: mit
Keywords: speech,recognition,tts,text-to-speech,audio,machine-learning,voice
Platform: any
License-File: LICENSE
Requires-Dist: speech_recognition>=3.10.0
Requires-Dist: pyttsx3>=2.90
Requires-Dist: librosa>=0.10.0
Requires-Dist: pydub>=0.25.0
Requires-Dist: numpy>=1.21.0
Requires-Dist: pyaudio>=0.2.11
Dynamic: license-file
